mlflow_deploifai/__init__.py
mlflow_deploifai/request_header_provider.py
mlflow_deploifai-0.0.3.dist-info/LICENSE
mlflow_deploifai-0.0.3.dist-info/METADATA
mlflow_deploifai-0.0.3.dist-info/WHEEL
mlflow_deploifai-0.0.3.dist-info/entry_points.txt
mlflow_deploifai-0.0.3.dist-info/top_level.txt
mlflow_deploifai-0.0.3.dist-info/RECORD
