Metadata-Version: 2.1
Name: mlflow-deploifai
Version: 0.0.3
Summary: Deploifai plugin for MLflow
Home-page: https://github.com/deploifai/mlflow-deploifai-plugin
Author: Deploifai Limited
Requires-Python: >=3.7
License-File: LICENSE
Requires-Dist: mlflow
